MANIFEST.in
requirements.txt
setup.py
django_tempus.egg-info/PKG-INFO
django_tempus.egg-info/SOURCES.txt
django_tempus.egg-info/dependency_links.txt
django_tempus.egg-info/requires.txt
django_tempus.egg-info/top_level.txt
tempus/__init__.py
tempus/middleware.py
tempus/models.py
tempus/utils.py
tempus/contrib/__init__.py
tempus/contrib/auto_login/__init__.py
tempus/contrib/auto_login/middleware.py
tempus/templatetags/__init__.py
tempus/templatetags/tempus_tag.py
tempus/tests/__init__.py
tempus/tests/middleware.py
tempus/tests/settings.py
tempus/tests/urls.py
tempus/tests/views.py