Metadata-Version: 1.1
Name: django-tempus
Version: 0.5.0
Summary: Django Tempus provides url tokens that triggers custom actions
Home-page: http://github.com/juanriaza/django-tempus
Author: Juan Riaza
Author-email: juanriaza@gmail.com
License: BSD
Platform: UNKNOWN
Classifier: Development Status :: 4 - Beta
Classifier: Environment :: Web Environment
Classifier: Framework :: Django
Classifier: Intended Audience :: Developers
Classifier: License :: OSI Approved :: BSD License
Classifier: Operating System :: OS Independent
Classifier: Programming Language :: Python
Classifier: Topic :: Internet :: WWW/HTTP
